[{"url":"https://so.toutiao.com/search?keyword=佩通坦被解职%20他信家族有何后手","word":"佩通坦被解职 他信家族有何后手"},{"url":"https://so.toutiao.com/search?keyword=外交部：菲方踩踏红线必将付出代价","word":"外交部：菲方踩踏红线必将付出代价"},{"url":"https://so.toutiao.com/search?keyword=6个关键词%20看懂这场重磅发布会","word":"6个关键词 看懂这场重磅发布会"},{"url":"https://so.toutiao.com/search?keyword=佩通坦回应被解职","word":"佩通坦回应被解职"},{"url":"https://so.toutiao.com/search?keyword=阅兵观礼名单公布%20缺席者谁会后悔","word":"阅兵观礼名单公布 缺席者谁会后悔"},{"url":"https://so.toutiao.com/search?keyword=《生万物》人物形象塑造有哪些亮点","word":"《生万物》人物形象塑造有哪些亮点"},{"url":"https://so.toutiao.com/search?keyword=为泰党提名泰国新总理人选","word":"为泰党提名泰国新总理人选"},{"url":"https://so.toutiao.com/search?keyword=九三阅兵临近日本为何急了","word":"九三阅兵临近日本为何急了"},{"url":"https://so.toutiao.com/search?keyword=官方支持老旧住房原拆原建%20专家解读","word":"官方支持老旧住房原拆原建 专家解读"},{"url":"https://so.toutiao.com/search?keyword=云南德宏洪灾后遍地畜牧死亡？不实","word":"云南德宏洪灾后遍地畜牧死亡？不实"},{"url":"https://so.toutiao.com/search?keyword=日本前首相将出席阅兵%20日方：不评论","word":"日本前首相将出席阅兵 日方：不评论"},{"url":"https://so.toutiao.com/search?keyword=佩通坦被解除泰国总理职务","word":"佩通坦被解除泰国总理职务"},{"url":"https://so.toutiao.com/search?keyword=外交部回应俄罗斯袭击乌克兰首都","word":"外交部回应俄罗斯袭击乌克兰首都"},{"url":"https://so.toutiao.com/search?keyword=国防部：九三阅兵邀请国民党抗日老兵","word":"国防部：九三阅兵邀请国民党抗日老兵"},{"url":"https://so.toutiao.com/search?keyword=特朗普取消特勤局对哈里斯保护","word":"特朗普取消特勤局对哈里斯保护"},{"url":"https://so.toutiao.com/search?keyword=你对吴艳妮在世锦赛的表现有何期待","word":"你对吴艳妮在世锦赛的表现有何期待"},{"url":"https://so.toutiao.com/search?keyword=韩方：将在九三阅兵留意与朝方接触","word":"韩方：将在九三阅兵留意与朝方接触"},{"url":"https://so.toutiao.com/search?keyword=俄军无人机拆出欧洲部件说明什么","word":"俄军无人机拆出欧洲部件说明什么"},{"url":"https://so.toutiao.com/search?keyword=优酸乳删除虞书欣相关内容？伊利回应","word":"优酸乳删除虞书欣相关内容？伊利回应"},{"url":"https://so.toutiao.com/search?keyword=马英九：中华儿女不容抗日历史被扭曲","word":"马英九：中华儿女不容抗日历史被扭曲"},{"url":"https://so.toutiao.com/search?keyword=外卖霸主美团究竟何去何从","word":"外卖霸主美团究竟何去何从"},{"url":"https://so.toutiao.com/search?keyword=佩通坦解职后露面%20微笑向记者问好","word":"佩通坦解职后露面 微笑向记者问好"},{"url":"https://so.toutiao.com/search?keyword=九三阅兵倒计时！这个“预告”必看","word":"九三阅兵倒计时！这个“预告”必看"},{"url":"https://so.toutiao.com/search?keyword=首批全新坦克500于成都正式交付","word":"首批全新坦克500于成都正式交付"},{"url":"https://so.toutiao.com/search?keyword=外卖狂欢的代价：巨头财报惨不忍睹","word":"外卖狂欢的代价：巨头财报惨不忍睹"},{"url":"https://so.toutiao.com/search?keyword=佩通坦解职如何影响中泰关系","word":"佩通坦解职如何影响中泰关系"},{"url":"https://so.toutiao.com/search?keyword=奥巴马：特朗普政府正出现危险趋势","word":"奥巴马：特朗普政府正出现危险趋势"},{"url":"https://so.toutiao.com/search?keyword=回顾历年阅兵式首个接受检阅阵列","word":"回顾历年阅兵式首个接受检阅阵列"},{"url":"https://so.toutiao.com/search?keyword=两女子花3万请24位陪爬登顶泰山","word":"两女子花3万请24位陪爬登顶泰山"},{"url":"https://so.toutiao.com/search?keyword=俄军猛轰基辅%20乌方为何要中方表态","word":"俄军猛轰基辅 乌方为何要中方表态"},{"url":"https://so.toutiao.com/search?keyword=中国重工拟于9月5日终止上市","word":"中国重工拟于9月5日终止上市"},{"url":"https://so.toutiao.com/search?keyword=莫迪访华为何不参加九三阅兵","word":"莫迪访华为何不参加九三阅兵"},{"url":"https://so.toutiao.com/search?keyword=上海试点电动自行车超速抓拍","word":"上海试点电动自行车超速抓拍"},{"url":"https://so.toutiao.com/search?keyword=为何说李在明才是真正的“高手”","word":"为何说李在明才是真正的“高手”"},{"url":"https://so.toutiao.com/search?keyword=中芯国际市值逼近万亿大关","word":"中芯国际市值逼近万亿大关"},{"url":"https://so.toutiao.com/search?keyword=人民币兑美元汇率升至近十个月新高","word":"人民币兑美元汇率升至近十个月新高"},{"url":"https://so.toutiao.com/search?keyword=中国必将统一的大势不可阻挡","word":"中国必将统一的大势不可阻挡"},{"url":"https://so.toutiao.com/search?keyword=男子踩踏丹霞地貌%20景区报警","word":"男子踩踏丹霞地貌 景区报警"},{"url":"https://so.toutiao.com/search?keyword=男子从数米高石头上跌落%20景区回应","word":"男子从数米高石头上跌落 景区回应"},{"url":"https://so.toutiao.com/search?keyword=印学者：莫迪访华具有里程碑的意义","word":"印学者：莫迪访华具有里程碑的意义"},{"url":"https://so.toutiao.com/search?keyword=泰国政坛的他信家族“魔咒”","word":"泰国政坛的他信家族“魔咒”"},{"url":"https://so.toutiao.com/search?keyword=马英九：赖清德应向台湾人民郑重道歉","word":"马英九：赖清德应向台湾人民郑重道歉"},{"url":"https://so.toutiao.com/search?keyword=李在明送美方的龟船上刻着6个汉字","word":"李在明送美方的龟船上刻着6个汉字"},{"url":"https://so.toutiao.com/search?keyword=佩通坦被解职%20他信家族会认输吗","word":"佩通坦被解职 他信家族会认输吗"},{"url":"https://so.toutiao.com/search?keyword=曝莫迪访日将获超10万亿日元投资承诺","word":"曝莫迪访日将获超10万亿日元投资承诺"},{"url":"https://so.toutiao.com/search?keyword=俄轰炸基辅欧盟大楼是威胁警告吗","word":"俄轰炸基辅欧盟大楼是威胁警告吗"},{"url":"https://so.toutiao.com/search?keyword=网友反映佛山一学校一间房住百人","word":"网友反映佛山一学校一间房住百人"},{"url":"https://so.toutiao.com/search?keyword=肖国栋：我还是想把冠军留在中国","word":"肖国栋：我还是想把冠军留在中国"},{"url":"https://so.toutiao.com/search?keyword=73岁唐国强一下车就对粉丝敬礼","word":"73岁唐国强一下车就对粉丝敬礼"},{"url":"https://so.toutiao.com/search?keyword=《中国企业社保白皮书2025》发布","word":"《中国企业社保白皮书2025》发布"},{"url":"https://so.toutiao.com/search?keyword=埃及13岁男孩干吃3包方便面后死亡","word":"埃及13岁男孩干吃3包方便面后死亡"},{"url":"https://so.toutiao.com/search?keyword=阿里Q2%20Non-Gaap净利润同比下降18%","word":"阿里Q2 Non-Gaap净利润同比下降18%"},{"url":"https://so.toutiao.com/search?keyword=日媒：美防长想与中国防长通话","word":"日媒：美防长想与中国防长通话"},{"url":"https://so.toutiao.com/search?keyword=柳春霞已任辽宁省司法厅党组书记","word":"柳春霞已任辽宁省司法厅党组书记"},{"url":"https://so.toutiao.com/search?keyword=阿里加码闪购后淘宝活跃消费者增25%","word":"阿里加码闪购后淘宝活跃消费者增25%"},{"url":"https://so.toutiao.com/search?keyword=台湾15岁少女遭露营地老板儿子性侵","word":"台湾15岁少女遭露营地老板儿子性侵"},{"url":"https://so.toutiao.com/search?keyword=阿里开发新AI芯片%20由国内企业代工","word":"阿里开发新AI芯片 由国内企业代工"},{"url":"https://so.toutiao.com/search?keyword=律师：七夕垃圾桶寻宝或涉嫌侵占罪","word":"律师：七夕垃圾桶寻宝或涉嫌侵占罪"},{"url":"https://so.toutiao.com/search?keyword=新股王寒武纪主动降温","word":"新股王寒武纪主动降温"},{"url":"https://so.toutiao.com/search?keyword=阿里公布AI投入进展","word":"阿里公布AI投入进展"},{"url":"https://so.toutiao.com/search?keyword=虞书欣自然堂直播延期","word":"虞书欣自然堂直播延期"},{"url":"https://so.toutiao.com/search?keyword=苏有朋为卖艺不卖身言论致歉","word":"苏有朋为卖艺不卖身言论致歉"},{"url":"https://so.toutiao.com/search?keyword=40天女婴重病%2000后父亲割肝救女","word":"40天女婴重病 00后父亲割肝救女"},{"url":"https://so.toutiao.com/search?keyword=月全食土星冲日等天象将在9月亮相","word":"月全食土星冲日等天象将在9月亮相"},{"url":"https://so.toutiao.com/search?keyword=中国境内首个被允许破产的人怎样了","word":"中国境内首个被允许破产的人怎样了"},{"url":"https://so.toutiao.com/search?keyword=极氪9X硬控外国卡宴车主","word":"极氪9X硬控外国卡宴车主"},{"url":"https://so.toutiao.com/search?keyword=华为上半年净利润371亿元","word":"华为上半年净利润371亿元"},{"url":"https://so.toutiao.com/search?keyword=顾客起诉胖东来免费筷子未标生产日期","word":"顾客起诉胖东来免费筷子未标生产日期"},{"url":"https://so.toutiao.com/search?keyword=外卖员戴恐怖面具取餐吓坏女店员","word":"外卖员戴恐怖面具取餐吓坏女店员"}]