[{"url":"https://so.toutiao.com/search?keyword=国家中医药管理局原局长于文明被查","word":"国家中医药管理局原局长于文明被查"},{"url":"https://so.toutiao.com/search?keyword=强奸杀害7岁女童的男子被执行死刑","word":"强奸杀害7岁女童的男子被执行死刑"},{"url":"https://so.toutiao.com/search?keyword=“未来在中国”何以成为外资共识","word":"“未来在中国”何以成为外资共识"},{"url":"https://so.toutiao.com/search?keyword=中考接送车与半挂车相撞致2死4伤","word":"中考接送车与半挂车相撞致2死4伤"},{"url":"https://so.toutiao.com/search?keyword=美拟取消芯片技术豁免反制中国稀土","word":"美拟取消芯片技术豁免反制中国稀土"},{"url":"https://so.toutiao.com/search?keyword=特朗普：美国袭击伊朗核设施","word":"特朗普：美国袭击伊朗核设施"},{"url":"https://so.toutiao.com/search?keyword=汪峰回应与宁静牵手","word":"汪峰回应与宁静牵手"},{"url":"https://so.toutiao.com/search?keyword=村民拆迁14年未安置索要过渡费被捕","word":"村民拆迁14年未安置索要过渡费被捕"},{"url":"https://so.toutiao.com/search?keyword=伊朗将打击美国在中东地区所有利益","word":"伊朗将打击美国在中东地区所有利益"},{"url":"https://so.toutiao.com/search?keyword=被名校提前录取获50万奖金？假的","word":"被名校提前录取获50万奖金？假的"},{"url":"https://so.toutiao.com/search?keyword=狗狗为报恩直接送一只狗崽","word":"狗狗为报恩直接送一只狗崽"},{"url":"https://so.toutiao.com/search?keyword=专家：美打击伊朗出于三方面考虑","word":"专家：美打击伊朗出于三方面考虑"},{"url":"https://so.toutiao.com/search?keyword=63岁马景涛直播时晕倒","word":"63岁马景涛直播时晕倒"},{"url":"https://so.toutiao.com/search?keyword=官方通报公司副总送货被压倒身亡","word":"官方通报公司副总送货被压倒身亡"},{"url":"https://so.toutiao.com/search?keyword=袭击后特朗普再次威胁伊朗","word":"袭击后特朗普再次威胁伊朗"},{"url":"https://so.toutiao.com/search?keyword=房产大V：新一波稳楼市大招来了","word":"房产大V：新一波稳楼市大招来了"},{"url":"https://so.toutiao.com/search?keyword=林允卡点为周星驰庆生","word":"林允卡点为周星驰庆生"},{"url":"https://so.toutiao.com/search?keyword=特朗普：伊朗核设施已被彻底摧毁","word":"特朗普：伊朗核设施已被彻底摧毁"},{"url":"https://so.toutiao.com/search?keyword=韩红痛斥歌手依赖耳机提示音","word":"韩红痛斥歌手依赖耳机提示音"},{"url":"https://so.toutiao.com/search?keyword=“卤鹅哥”给刀郎粉丝投喂荣昌卤鹅","word":"“卤鹅哥”给刀郎粉丝投喂荣昌卤鹅"},{"url":"https://so.toutiao.com/search?keyword=美军投掷6枚钻地弹袭击伊朗核设施","word":"美军投掷6枚钻地弹袭击伊朗核设施"},{"url":"https://so.toutiao.com/search?keyword=特朗普动手了%20原油黄金和美股会如何","word":"特朗普动手了 原油黄金和美股会如何"},{"url":"https://so.toutiao.com/search?keyword=美驻中东空军基地军机大量消失","word":"美驻中东空军基地军机大量消失"},{"url":"https://so.toutiao.com/search?keyword=美轰炸伊朗核设施直接成本5亿美元","word":"美轰炸伊朗核设施直接成本5亿美元"},{"url":"https://so.toutiao.com/search?keyword=王欣瑜为何在草地变强","word":"王欣瑜为何在草地变强"},{"url":"https://so.toutiao.com/search?keyword=马匹被激流冲走%20三分钟后脱险上岸","word":"马匹被激流冲走 三分钟后脱险上岸"},{"url":"https://so.toutiao.com/search?keyword=专家：美空袭伊朗核设施是火上浇油","word":"专家：美空袭伊朗核设施是火上浇油"},{"url":"https://so.toutiao.com/search?keyword=贵州榕江齐心协力抢险救灾","word":"贵州榕江齐心协力抢险救灾"},{"url":"https://so.toutiao.com/search?keyword=男方资助女子近65万留学分手后索回","word":"男方资助女子近65万留学分手后索回"},{"url":"https://so.toutiao.com/search?keyword=牛弹琴：美对伊动手中东或彻底爆炸","word":"牛弹琴：美对伊动手中东或彻底爆炸"},{"url":"https://so.toutiao.com/search?keyword=“苏超”爆火“狮超”也来了","word":"“苏超”爆火“狮超”也来了"},{"url":"https://so.toutiao.com/search?keyword=以色列升级全国戒备状态","word":"以色列升级全国戒备状态"},{"url":"https://so.toutiao.com/search?keyword=白宫公布特朗普在战情室照片","word":"白宫公布特朗普在战情室照片"},{"url":"https://so.toutiao.com/search?keyword=暴雨后人员被困车顶%20冲走瞬间被救起","word":"暴雨后人员被困车顶 冲走瞬间被救起"},{"url":"https://so.toutiao.com/search?keyword=姚晨去年歪打正着买到Labubu限量版","word":"姚晨去年歪打正着买到Labubu限量版"},{"url":"https://so.toutiao.com/search?keyword=美军B2轰炸机参与袭击伊朗核设施","word":"美军B2轰炸机参与袭击伊朗核设施"},{"url":"https://so.toutiao.com/search?keyword=陈熠3-2战胜张本美和","word":"陈熠3-2战胜张本美和"},{"url":"https://so.toutiao.com/search?keyword=常州苏超五连败%20一景区推出光头免票","word":"常州苏超五连败 一景区推出光头免票"},{"url":"https://so.toutiao.com/search?keyword=伊朗发布福尔多核设施遭袭后画面","word":"伊朗发布福尔多核设施遭袭后画面"},{"url":"https://so.toutiao.com/search?keyword=佩通坦会因“录音风波”下台吗","word":"佩通坦会因“录音风波”下台吗"},{"url":"https://so.toutiao.com/search?keyword=伊朗最高领袖顾问呼吁袭击美军舰艇","word":"伊朗最高领袖顾问呼吁袭击美军舰艇"},{"url":"https://so.toutiao.com/search?keyword=美在伊朗投下的钻地弹威力仅次核武","word":"美在伊朗投下的钻地弹威力仅次核武"},{"url":"https://so.toutiao.com/search?keyword=伊朗称中东美国人都是“合法目标”","word":"伊朗称中东美国人都是“合法目标”"},{"url":"https://so.toutiao.com/search?keyword=什叶派最高宗教领袖：别碰伊朗领导层","word":"什叶派最高宗教领袖：别碰伊朗领导层"},{"url":"https://so.toutiao.com/search?keyword=美军直接出手伊朗核设施真的毁了吗","word":"美军直接出手伊朗核设施真的毁了吗"},{"url":"https://so.toutiao.com/search?keyword=以军称伊朗开始发动“报复性袭击”","word":"以军称伊朗开始发动“报复性袭击”"},{"url":"https://so.toutiao.com/search?keyword=古特雷斯：对美袭击伊朗深感震惊","word":"古特雷斯：对美袭击伊朗深感震惊"},{"url":"https://so.toutiao.com/search?keyword=评论员：特朗普让伊朗放松警惕","word":"评论员：特朗普让伊朗放松警惕"},{"url":"https://so.toutiao.com/search?keyword=美媒称以色列经济被“炸”停","word":"美媒称以色列经济被“炸”停"},{"url":"https://so.toutiao.com/search?keyword=伊朗称击中以色列14个战略军事目标","word":"伊朗称击中以色列14个战略军事目标"},{"url":"https://so.toutiao.com/search?keyword=王欣瑜为何能在草地球场突然进化","word":"王欣瑜为何能在草地球场突然进化"},{"url":"https://so.toutiao.com/search?keyword=广西绿化带里都是水果","word":"广西绿化带里都是水果"},{"url":"https://so.toutiao.com/search?keyword=蔡正元：美债敲响丧钟热钱涌入中国","word":"蔡正元：美债敲响丧钟热钱涌入中国"},{"url":"https://so.toutiao.com/search?keyword=专家：伊朗想靠俄却不敢靠","word":"专家：伊朗想靠俄却不敢靠"},{"url":"https://so.toutiao.com/search?keyword=博主：二号台风圣帕或近期生成","word":"博主：二号台风圣帕或近期生成"},{"url":"https://so.toutiao.com/search?keyword=陕西中考首日家长手捧鲜花等候","word":"陕西中考首日家长手捧鲜花等候"},{"url":"https://so.toutiao.com/search?keyword=大V：空调企业应防范印度偷学技术","word":"大V：空调企业应防范印度偷学技术"},{"url":"https://so.toutiao.com/search?keyword=校长为支教回国女孩办一人毕业礼","word":"校长为支教回国女孩办一人毕业礼"},{"url":"https://so.toutiao.com/search?keyword=美采购商：关税再高我也选中国","word":"美采购商：关税再高我也选中国"},{"url":"https://so.toutiao.com/search?keyword=中国女篮靠身高打法能否走长远","word":"中国女篮靠身高打法能否走长远"},{"url":"https://so.toutiao.com/search?keyword=苏超常州还剩多少“笔画”","word":"苏超常州还剩多少“笔画”"},{"url":"https://so.toutiao.com/search?keyword=4S店两销售诱导40余人转账超300万","word":"4S店两销售诱导40余人转账超300万"},{"url":"https://so.toutiao.com/search?keyword=你爱吃哪种荔枝","word":"你爱吃哪种荔枝"},{"url":"https://so.toutiao.com/search?keyword=伊朗称福尔多核设施仅地上部分受损","word":"伊朗称福尔多核设施仅地上部分受损"},{"url":"https://so.toutiao.com/search?keyword=内塔尼亚胡感谢特朗普","word":"内塔尼亚胡感谢特朗普"},{"url":"https://so.toutiao.com/search?keyword=伊朗称已提前对三个核设施进行疏散","word":"伊朗称已提前对三个核设施进行疏散"},{"url":"https://so.toutiao.com/search?keyword=以伊进入消耗战可能性增加","word":"以伊进入消耗战可能性增加"},{"url":"https://so.toutiao.com/search?keyword=以数十万美元导弹击落伊廉价无人机","word":"以数十万美元导弹击落伊廉价无人机"},{"url":"https://so.toutiao.com/search?keyword=哈马斯强烈谴责美国袭击伊朗","word":"哈马斯强烈谴责美国袭击伊朗"},{"url":"https://so.toutiao.com/search?keyword=男子带75万元现金出境被查获","word":"男子带75万元现金出境被查获"},{"url":"https://so.toutiao.com/search?keyword=专家：印度对巴基斯坦采取耍无赖政策","word":"专家：印度对巴基斯坦采取耍无赖政策"},{"url":"https://so.toutiao.com/search?keyword=专家：印度急断与台合作有何目的","word":"专家：印度急断与台合作有何目的"},{"url":"https://so.toutiao.com/search?keyword=“错换人生28年”案双方当事人发声","word":"“错换人生28年”案双方当事人发声"},{"url":"https://so.toutiao.com/search?keyword=神秘人向华中科技大学捐1.8亿","word":"神秘人向华中科技大学捐1.8亿"},{"url":"https://so.toutiao.com/search?keyword=男子携带75万元现金出境被现场查获","word":"男子携带75万元现金出境被现场查获"},{"url":"https://so.toutiao.com/search?keyword=专家解读美军轰炸伊朗核设施","word":"专家解读美军轰炸伊朗核设施"},{"url":"https://so.toutiao.com/search?keyword=孩子摘没熟的杏玩被树主人叫家长","word":"孩子摘没熟的杏玩被树主人叫家长"},{"url":"https://so.toutiao.com/search?keyword=你怎么看拿王虹和韦东奕比较的现象","word":"你怎么看拿王虹和韦东奕比较的现象"},{"url":"https://so.toutiao.com/search?keyword=苏超观众称常州队表现比国足强","word":"苏超观众称常州队表现比国足强"},{"url":"https://so.toutiao.com/search?keyword=美为何此时袭击伊朗核设施","word":"美为何此时袭击伊朗核设施"},{"url":"https://so.toutiao.com/search?keyword=蔡正元：解放军今年或进三航母时代","word":"蔡正元：解放军今年或进三航母时代"},{"url":"https://so.toutiao.com/search?keyword=印度称绝不恢复履行印度河用水条约","word":"印度称绝不恢复履行印度河用水条约"},{"url":"https://so.toutiao.com/search?keyword=贵州荔波特大暴雨%20受灾群众已转移","word":"贵州荔波特大暴雨 受灾群众已转移"},{"url":"https://so.toutiao.com/search?keyword=媒体人：付豪已登记结婚","word":"媒体人：付豪已登记结婚"},{"url":"https://so.toutiao.com/search?keyword=特朗普曾多少次许诺两周内要做大事","word":"特朗普曾多少次许诺两周内要做大事"},{"url":"https://so.toutiao.com/search?keyword=为何香港积极推出《稳定币条例》","word":"为何香港积极推出《稳定币条例》"},{"url":"https://so.toutiao.com/search?keyword=以色列与伊朗有什么历史恩怨","word":"以色列与伊朗有什么历史恩怨"},{"url":"https://so.toutiao.com/search?keyword=美媒：哈梅内伊藏身地堡%20已提名接班人","word":"美媒：哈梅内伊藏身地堡 已提名接班人"},{"url":"https://so.toutiao.com/search?keyword=特朗普称美高官搞错伊朗核武器情报","word":"特朗普称美高官搞错伊朗核武器情报"},{"url":"https://so.toutiao.com/search?keyword=在以中国工人：导弹常半夜搞突袭","word":"在以中国工人：导弹常半夜搞突袭"},{"url":"https://so.toutiao.com/search?keyword=美袭击伊朗后美以领导人通话","word":"美袭击伊朗后美以领导人通话"},{"url":"https://so.toutiao.com/search?keyword=以伊冲突是否会长期化","word":"以伊冲突是否会长期化"},{"url":"https://so.toutiao.com/search?keyword=美方下场%20一文速览以伊局势突变","word":"美方下场 一文速览以伊局势突变"},{"url":"https://so.toutiao.com/search?keyword=以色列将在全国设1000个路边避难所","word":"以色列将在全国设1000个路边避难所"},{"url":"https://so.toutiao.com/search?keyword=步行者vs雷霆G7前瞻","word":"步行者vs雷霆G7前瞻"},{"url":"https://so.toutiao.com/search?keyword=万茜获得金爵奖最佳女演员奖","word":"万茜获得金爵奖最佳女演员奖"},{"url":"https://so.toutiao.com/search?keyword=国米2-1浦和红钻仅25090名观众","word":"国米2-1浦和红钻仅25090名观众"},{"url":"https://so.toutiao.com/search?keyword=伊朗伊斯法罕离心机制造车间遭袭击","word":"伊朗伊斯法罕离心机制造车间遭袭击"},{"url":"https://so.toutiao.com/search?keyword=曝美已与伊接触%20否认谋求政权更迭","word":"曝美已与伊接触 否认谋求政权更迭"},{"url":"https://so.toutiao.com/search?keyword=伊朗官员称已做好准备应对美国下场","word":"伊朗官员称已做好准备应对美国下场"},{"url":"https://so.toutiao.com/search?keyword=苏超成“吸金兽”%20十三太保凭什么","word":"苏超成“吸金兽” 十三太保凭什么"},{"url":"https://so.toutiao.com/search?keyword=以航空计划复飞特拉维夫机场国际航班","word":"以航空计划复飞特拉维夫机场国际航班"},{"url":"https://so.toutiao.com/search?keyword=警方通报客车发生事故致2死4伤","word":"警方通报客车发生事故致2死4伤"},{"url":"https://so.toutiao.com/search?keyword=沈阳90后女孩养了近二十种宠物","word":"沈阳90后女孩养了近二十种宠物"},{"url":"https://so.toutiao.com/search?keyword=李梦落选中国女篮谁损失最大","word":"李梦落选中国女篮谁损失最大"},{"url":"https://so.toutiao.com/search?keyword=美对伊核设施打击“成功”？专家解读","word":"美对伊核设施打击“成功”？专家解读"},{"url":"https://so.toutiao.com/search?keyword=监视居住期间杀害堂妹男子被执行死刑","word":"监视居住期间杀害堂妹男子被执行死刑"},{"url":"https://so.toutiao.com/search?keyword=美联储政策如何影响普通人的钱袋子","word":"美联储政策如何影响普通人的钱袋子"},{"url":"https://so.toutiao.com/search?keyword=黄渤黄晓明首次同台颁奖","word":"黄渤黄晓明首次同台颁奖"},{"url":"https://so.toutiao.com/search?keyword=中央气象台暴雨和高温预警齐发","word":"中央气象台暴雨和高温预警齐发"},{"url":"https://so.toutiao.com/search?keyword=联合国专家谴责以色列袭击伊朗","word":"联合国专家谴责以色列袭击伊朗"},{"url":"https://so.toutiao.com/search?keyword=以军空袭伊朗核设施难度有多大","word":"以军空袭伊朗核设施难度有多大"},{"url":"https://so.toutiao.com/search?keyword=特朗普：伊朗已再无福尔多核设施","word":"特朗普：伊朗已再无福尔多核设施"},{"url":"https://so.toutiao.com/search?keyword=“国补”点燃县域家电消费市场","word":"“国补”点燃县域家电消费市场"},{"url":"https://so.toutiao.com/search?keyword=曝美军6架B-2从本土飞往关岛","word":"曝美军6架B-2从本土飞往关岛"},{"url":"https://so.toutiao.com/search?keyword=特朗普称伊朗须同意结束战争","word":"特朗普称伊朗须同意结束战争"},{"url":"https://so.toutiao.com/search?keyword=洪森为何算计年轻的泰国总理","word":"洪森为何算计年轻的泰国总理"},{"url":"https://so.toutiao.com/search?keyword=全身85%烧伤女孩结婚了","word":"全身85%烧伤女孩结婚了"},{"url":"https://so.toutiao.com/search?keyword=伊导弹极速突防以民众惊恐大喊","word":"伊导弹极速突防以民众惊恐大喊"},{"url":"https://so.toutiao.com/search?keyword=印度少女遭14人强奸两年现怀孕8月","word":"印度少女遭14人强奸两年现怀孕8月"},{"url":"https://so.toutiao.com/search?keyword=接亲娘家堵门一小时%20新郎稳如泰山","word":"接亲娘家堵门一小时 新郎稳如泰山"},{"url":"https://so.toutiao.com/search?keyword=克林顿：以总理欲借打伊朗延长执政","word":"克林顿：以总理欲借打伊朗延长执政"},{"url":"https://so.toutiao.com/search?keyword=苏超盐城队17岁门将连续神扑救","word":"苏超盐城队17岁门将连续神扑救"},{"url":"https://so.toutiao.com/search?keyword=全球每三颗荔枝就有一颗来自广东","word":"全球每三颗荔枝就有一颗来自广东"},{"url":"https://so.toutiao.com/search?keyword=以总理站在被炸毁科研所废墟前苦笑","word":"以总理站在被炸毁科研所废墟前苦笑"},{"url":"https://so.toutiao.com/search?keyword=男子嫌机票太贵%20连偷8辆车当坐驾","word":"男子嫌机票太贵 连偷8辆车当坐驾"},{"url":"https://so.toutiao.com/search?keyword=女子分手后被前男友母亲索要留学费","word":"女子分手后被前男友母亲索要留学费"},{"url":"https://so.toutiao.com/search?keyword=亲历撤侨中国人称其他外国人很羡慕","word":"亲历撤侨中国人称其他外国人很羡慕"},{"url":"https://so.toutiao.com/search?keyword=在伊华人：挨过以三板斧后伊朗挺住了","word":"在伊华人：挨过以三板斧后伊朗挺住了"},{"url":"https://so.toutiao.com/search?keyword=村里“汪汪队”合力驱赶藏马熊","word":"村里“汪汪队”合力驱赶藏马熊"},{"url":"https://so.toutiao.com/search?keyword=白鹿“现身”常州主场呼吁文明观赛","word":"白鹿“现身”常州主场呼吁文明观赛"},{"url":"https://so.toutiao.com/search?keyword=伊朗第17阶段打击用了30枚导弹","word":"伊朗第17阶段打击用了30枚导弹"},{"url":"https://so.toutiao.com/search?keyword=伊朗有多少中式武器","word":"伊朗有多少中式武器"},{"url":"https://so.toutiao.com/search?keyword=你对李梦落选国家队有何看法","word":"你对李梦落选国家队有何看法"},{"url":"https://so.toutiao.com/search?keyword=以色列两个“战略要点”遭袭","word":"以色列两个“战略要点”遭袭"},{"url":"https://so.toutiao.com/search?keyword=伊朗高官：特朗普一个电话就能止战","word":"伊朗高官：特朗普一个电话就能止战"},{"url":"https://so.toutiao.com/search?keyword=伊朗2次地震跟地下核试验有关系吗","word":"伊朗2次地震跟地下核试验有关系吗"},{"url":"https://so.toutiao.com/search?keyword=也门百万人游行声援巴勒斯坦和伊朗","word":"也门百万人游行声援巴勒斯坦和伊朗"},{"url":"https://so.toutiao.com/search?keyword=以色列的未来在哪里","word":"以色列的未来在哪里"},{"url":"https://so.toutiao.com/search?keyword=IAEA：袭击伊朗核电站恐引严重后果","word":"IAEA：袭击伊朗核电站恐引严重后果"},{"url":"https://so.toutiao.com/search?keyword=俄称若乌用脏弹将以战术核武器回击","word":"俄称若乌用脏弹将以战术核武器回击"},{"url":"https://so.toutiao.com/search?keyword=毕业典礼食堂阿姨真挚叮嘱引同学落泪","word":"毕业典礼食堂阿姨真挚叮嘱引同学落泪"},{"url":"https://so.toutiao.com/search?keyword=俄方就伊以冲突发出“最强硬表态”","word":"俄方就伊以冲突发出“最强硬表态”"},{"url":"https://so.toutiao.com/search?keyword=博主：佩通坦与洪森通话犯三个大忌","word":"博主：佩通坦与洪森通话犯三个大忌"},{"url":"https://so.toutiao.com/search?keyword=北京大学华侨大学男篮会师CUBAL决赛","word":"北京大学华侨大学男篮会师CUBAL决赛"},{"url":"https://so.toutiao.com/search?keyword=伊朗导弹与以防空系统“擦肩而过”","word":"伊朗导弹与以防空系统“擦肩而过”"},{"url":"https://so.toutiao.com/search?keyword=女星那尔那茜涉嫌高考报名材料造假","word":"女星那尔那茜涉嫌高考报名材料造假"},{"url":"https://so.toutiao.com/search?keyword=“苏超”：常州0-4送南京登顶","word":"“苏超”：常州0-4送南京登顶"},{"url":"https://so.toutiao.com/search?keyword=九寨沟景区发生大巴坠崖事故？谣言","word":"九寨沟景区发生大巴坠崖事故？谣言"},{"url":"https://so.toutiao.com/search?keyword=霍震霆曝小儿子霍启仁已结婚","word":"霍震霆曝小儿子霍启仁已结婚"},{"url":"https://so.toutiao.com/search?keyword=连人带车被洪水冲走女子已遇难","word":"连人带车被洪水冲走女子已遇难"},{"url":"https://so.toutiao.com/search?keyword=蚊子大小无人机问世意味着什么","word":"蚊子大小无人机问世意味着什么"},{"url":"https://so.toutiao.com/search?keyword=南通支云主场积水严重%20场内全是水坑","word":"南通支云主场积水严重 场内全是水坑"},{"url":"https://so.toutiao.com/search?keyword=警方回应老人水中摔倒民警未搀扶","word":"警方回应老人水中摔倒民警未搀扶"},{"url":"https://so.toutiao.com/search?keyword=以军高官：须准备与伊朗打持久战","word":"以军高官：须准备与伊朗打持久战"},{"url":"https://so.toutiao.com/search?keyword=以色列战略转向%20欲重塑中东格局吗","word":"以色列战略转向 欲重塑中东格局吗"},{"url":"https://so.toutiao.com/search?keyword=伊朗开出谈判条件","word":"伊朗开出谈判条件"},{"url":"https://so.toutiao.com/search?keyword=国防科大研制微型机器人释放何信号","word":"国防科大研制微型机器人释放何信号"},{"url":"https://so.toutiao.com/search?keyword=专家：特朗普让内塔尼亚胡很没面子","word":"专家：特朗普让内塔尼亚胡很没面子"},{"url":"https://so.toutiao.com/search?keyword=打击伊朗只需下令%20美到底还在等什么","word":"打击伊朗只需下令 美到底还在等什么"},{"url":"https://so.toutiao.com/search?keyword=三连胜！中国女排3比1击败日本女排","word":"三连胜！中国女排3比1击败日本女排"},{"url":"https://so.toutiao.com/search?keyword=公司回应宿舍厕所被曝装摄像头","word":"公司回应宿舍厕所被曝装摄像头"},{"url":"https://so.toutiao.com/search?keyword=以色列证实伊朗导弹携带集束弹头","word":"以色列证实伊朗导弹携带集束弹头"},{"url":"https://so.toutiao.com/search?keyword=足协杯广州豹2-0津门虎晋级","word":"足协杯广州豹2-0津门虎晋级"},{"url":"https://so.toutiao.com/search?keyword=伊朗地震引发核试验猜测","word":"伊朗地震引发核试验猜测"},{"url":"https://so.toutiao.com/search?keyword=李雪琴礼服造型亮相又被夸瘦了","word":"李雪琴礼服造型亮相又被夸瘦了"},{"url":"https://so.toutiao.com/search?keyword=在美伊对抗中伊朗有胜算吗","word":"在美伊对抗中伊朗有胜算吗"},{"url":"https://so.toutiao.com/search?keyword=专家：非常不解美国约束留学生签证","word":"专家：非常不解美国约束留学生签证"},{"url":"https://so.toutiao.com/search?keyword=南京大哥：都应该感受下苏超的快乐","word":"南京大哥：都应该感受下苏超的快乐"},{"url":"https://so.toutiao.com/search?keyword=巴为何推荐特朗普角逐诺贝尔和平奖","word":"巴为何推荐特朗普角逐诺贝尔和平奖"},{"url":"https://so.toutiao.com/search?keyword=三航母体系对国土安全意味着什么","word":"三航母体系对国土安全意味着什么"},{"url":"https://so.toutiao.com/search?keyword=奥巴马暗批特朗普政府","word":"奥巴马暗批特朗普政府"},{"url":"https://so.toutiao.com/search?keyword=台名嘴：以色列人以为战争很远","word":"台名嘴：以色列人以为战争很远"},{"url":"https://so.toutiao.com/search?keyword=苏超宿迁球迷全身盔甲披挂上阵","word":"苏超宿迁球迷全身盔甲披挂上阵"},{"url":"https://so.toutiao.com/search?keyword=两架B-2从美本土飞往关岛美军基地","word":"两架B-2从美本土飞往关岛美军基地"},{"url":"https://so.toutiao.com/search?keyword=女子错骑他人电动车闹“乌龙”","word":"女子错骑他人电动车闹“乌龙”"},{"url":"https://so.toutiao.com/search?keyword=韩菲儿2-3不敌长崎美柚","word":"韩菲儿2-3不敌长崎美柚"},{"url":"https://so.toutiao.com/search?keyword=北京送考车辆违反尾号限行可免罚","word":"北京送考车辆违反尾号限行可免罚"},{"url":"https://so.toutiao.com/search?keyword=普京：俄中并非在构建全新世界秩序","word":"普京：俄中并非在构建全新世界秩序"},{"url":"https://so.toutiao.com/search?keyword=陈熠晋级WTT卢布尔雅那站女单8强","word":"陈熠晋级WTT卢布尔雅那站女单8强"},{"url":"https://so.toutiao.com/search?keyword=多地遭遇持续强降雨%20救援现场直击","word":"多地遭遇持续强降雨 救援现场直击"},{"url":"https://so.toutiao.com/search?keyword=送考老师身着红衣为考生送祝福","word":"送考老师身着红衣为考生送祝福"},{"url":"https://so.toutiao.com/search?keyword=泰国总理前往边境地区会见军区司令","word":"泰国总理前往边境地区会见军区司令"},{"url":"https://so.toutiao.com/search?keyword=普京：俄士兵脚踩之地就属于俄罗斯","word":"普京：俄士兵脚踩之地就属于俄罗斯"},{"url":"https://so.toutiao.com/search?keyword=伊朗恢复全国网络服务","word":"伊朗恢复全国网络服务"},{"url":"https://so.toutiao.com/search?keyword=伊朗的战果究竟有多大","word":"伊朗的战果究竟有多大"},{"url":"https://so.toutiao.com/search?keyword=苏超彻底暴露了江苏的家底","word":"苏超彻底暴露了江苏的家底"},{"url":"https://so.toutiao.com/search?keyword=常州队背后：城市民间足球的冷与热","word":"常州队背后：城市民间足球的冷与热"},{"url":"https://so.toutiao.com/search?keyword=美代表想指责伊朗说成以色列","word":"美代表想指责伊朗说成以色列"},{"url":"https://so.toutiao.com/search?keyword=专家：美航母将压境%20伊朗做最坏打算","word":"专家：美航母将压境 伊朗做最坏打算"},{"url":"https://so.toutiao.com/search?keyword=飞行员首次驾战机飞上蓝天放声高歌","word":"飞行员首次驾战机飞上蓝天放声高歌"},{"url":"https://so.toutiao.com/search?keyword=马斯克会跑路到俄罗斯吗","word":"马斯克会跑路到俄罗斯吗"},{"url":"https://so.toutiao.com/search?keyword=外地小哥感慨哈尔滨清凉","word":"外地小哥感慨哈尔滨清凉"},{"url":"https://so.toutiao.com/search?keyword=广东疾控公布一例狂犬病致死病例","word":"广东疾控公布一例狂犬病致死病例"},{"url":"https://so.toutiao.com/search?keyword=夏思凝：处于低谷时四面都是上坡路","word":"夏思凝：处于低谷时四面都是上坡路"},{"url":"https://so.toutiao.com/search?keyword=刀迷用直升机给刀郎应援","word":"刀迷用直升机给刀郎应援"},{"url":"https://so.toutiao.com/search?keyword=毕业典礼爆火的青花瓷女孩毕业了","word":"毕业典礼爆火的青花瓷女孩毕业了"},{"url":"https://so.toutiao.com/search?keyword=以军公布伊斯法罕核设施遇袭后画面","word":"以军公布伊斯法罕核设施遇袭后画面"},{"url":"https://so.toutiao.com/search?keyword=媒体人：洪森“离间计”起了反作用","word":"媒体人：洪森“离间计”起了反作用"},{"url":"https://so.toutiao.com/search?keyword=女子回应和老公前妻合伙开饭店","word":"女子回应和老公前妻合伙开饭店"},{"url":"https://so.toutiao.com/search?keyword=大爷用铁杆打空调安装师傅%20社区回应","word":"大爷用铁杆打空调安装师傅 社区回应"},{"url":"https://so.toutiao.com/search?keyword=游客惊扰大熊猫殴打劝阻者","word":"游客惊扰大熊猫殴打劝阻者"},{"url":"https://so.toutiao.com/search?keyword=普京：准备支持伊朗发展和平核能","word":"普京：准备支持伊朗发展和平核能"},{"url":"https://so.toutiao.com/search?keyword=华为对OS的野心比苹果还疯狂吗","word":"华为对OS的野心比苹果还疯狂吗"},{"url":"https://so.toutiao.com/search?keyword=女生毕业典礼上深情演唱《壁上观》","word":"女生毕业典礼上深情演唱《壁上观》"},{"url":"https://so.toutiao.com/search?keyword=男子上班路上偶遇战机呼啸掠过","word":"男子上班路上偶遇战机呼啸掠过"}]