[{"url":"https://so.toutiao.com/search?keyword=日方没有任何资格对中国台湾置喙","word":"日方没有任何资格对中国台湾置喙"},{"url":"https://so.toutiao.com/search?keyword=武汉病毒研究所发现对尼帕有效药物","word":"武汉病毒研究所发现对尼帕有效药物"},{"url":"https://so.toutiao.com/search?keyword=中部地区高质量发展动能强劲","word":"中部地区高质量发展动能强劲"},{"url":"https://so.toutiao.com/search?keyword=英国首相斯塔默将访华","word":"英国首相斯塔默将访华"},{"url":"https://so.toutiao.com/search?keyword=10岁抗癌“小王子”豪豪离世","word":"10岁抗癌“小王子”豪豪离世"},{"url":"https://so.toutiao.com/search?keyword=刘强东老家大喇叭叫乡亲领年货","word":"刘强东老家大喇叭叫乡亲领年货"},{"url":"https://so.toutiao.com/search?keyword=男子彩票中800万交给妻子淡定上班","word":"男子彩票中800万交给妻子淡定上班"},{"url":"https://so.toutiao.com/search?keyword=《职工带薪年休假条例》将修订","word":"《职工带薪年休假条例》将修订"},{"url":"https://so.toutiao.com/search?keyword=中国代表向日方发出灵魂四问","word":"中国代表向日方发出灵魂四问"},{"url":"https://so.toutiao.com/search?keyword=研究发现午睡正在悄悄拉开大脑年龄差","word":"研究发现午睡正在悄悄拉开大脑年龄差"},{"url":"https://so.toutiao.com/search?keyword=中国关工委辟谣办奥林匹克数学联赛","word":"中国关工委辟谣办奥林匹克数学联赛"},{"url":"https://so.toutiao.com/search?keyword=女子在餐厅女卫生间发现不当标语牌","word":"女子在餐厅女卫生间发现不当标语牌"},{"url":"https://so.toutiao.com/search?keyword=印度捕获9蝙蝠%201只有尼帕病毒抗体","word":"印度捕获9蝙蝠 1只有尼帕病毒抗体"},{"url":"https://so.toutiao.com/search?keyword=香港4名公务员表现欠佳被着令退休","word":"香港4名公务员表现欠佳被着令退休"},{"url":"https://so.toutiao.com/search?keyword=我国成功研制场强35.6T全超导磁体","word":"我国成功研制场强35.6T全超导磁体"},{"url":"https://so.toutiao.com/search?keyword=中国网友称滞留日本：航班大量取消","word":"中国网友称滞留日本：航班大量取消"},{"url":"https://so.toutiao.com/search?keyword=男子路遇“孤独婚车”主动为其开道","word":"男子路遇“孤独婚车”主动为其开道"},{"url":"https://so.toutiao.com/search?keyword=日本熊猫迷坚信熊猫会再来日本","word":"日本熊猫迷坚信熊猫会再来日本"},{"url":"https://so.toutiao.com/search?keyword=商务部部长让芬兰企业畅所直言","word":"商务部部长让芬兰企业畅所直言"},{"url":"https://so.toutiao.com/search?keyword=专家：尼帕病毒输入风险总体可控","word":"专家：尼帕病毒输入风险总体可控"},{"url":"https://so.toutiao.com/search?keyword=戚薇撞脸金晨","word":"戚薇撞脸金晨"},{"url":"https://so.toutiao.com/search?keyword=芬兰总理访华抽空去了一趟故宫","word":"芬兰总理访华抽空去了一趟故宫"},{"url":"https://so.toutiao.com/search?keyword=香港内地事务局长曾国卫被免职","word":"香港内地事务局长曾国卫被免职"},{"url":"https://so.toutiao.com/search?keyword=广东江门回应山上发现数米长蟒蛇","word":"广东江门回应山上发现数米长蟒蛇"},{"url":"https://so.toutiao.com/search?keyword=专家：春节出行非必要不前往疫区","word":"专家：春节出行非必要不前往疫区"},{"url":"https://so.toutiao.com/search?keyword=白银一度暴涨14%至近118美元","word":"白银一度暴涨14%至近118美元"},{"url":"https://so.toutiao.com/search?keyword=匈牙利与乌克兰还有和解的可能吗","word":"匈牙利与乌克兰还有和解的可能吗"},{"url":"https://so.toutiao.com/search?keyword=比亚迪“大唐”实车曝光","word":"比亚迪“大唐”实车曝光"},{"url":"https://so.toutiao.com/search?keyword=美元资产危机是否缓解","word":"美元资产危机是否缓解"},{"url":"https://so.toutiao.com/search?keyword=父亲因怀疑女儿用纸擦头发暴怒","word":"父亲因怀疑女儿用纸擦头发暴怒"},{"url":"https://so.toutiao.com/search?keyword=日本因高致病性禽流感扑杀超10万鹌鹑","word":"日本因高致病性禽流感扑杀超10万鹌鹑"},{"url":"https://so.toutiao.com/search?keyword=安踏收购彪马能否撬开欧美市场","word":"安踏收购彪马能否撬开欧美市场"},{"url":"https://so.toutiao.com/search?keyword=英首相戴墨镜说法语调侃马克龙","word":"英首相戴墨镜说法语调侃马克龙"},{"url":"https://so.toutiao.com/search?keyword=小伙提醒大妈衣服上英文单词不合适","word":"小伙提醒大妈衣服上英文单词不合适"},{"url":"https://so.toutiao.com/search?keyword=蒋万安回应卓荣泰喊“台湾101”","word":"蒋万安回应卓荣泰喊“台湾101”"},{"url":"https://so.toutiao.com/search?keyword=美国认定加拿大纵容中国倾销","word":"美国认定加拿大纵容中国倾销"},{"url":"https://so.toutiao.com/search?keyword=妻子谈霍诺德登顶台北101：下不为例","word":"妻子谈霍诺德登顶台北101：下不为例"},{"url":"https://so.toutiao.com/search?keyword=国家级疾控专家团入驻乌鲁木齐","word":"国家级疾控专家团入驻乌鲁木齐"},{"url":"https://so.toutiao.com/search?keyword=欧盟2027年全面禁俄气有何影响","word":"欧盟2027年全面禁俄气有何影响"},{"url":"https://so.toutiao.com/search?keyword=寒潮下美国人极端天气自救清单火了","word":"寒潮下美国人极端天气自救清单火了"},{"url":"https://so.toutiao.com/search?keyword=医生解读女子受冷后手指变惨白","word":"医生解读女子受冷后手指变惨白"},{"url":"https://so.toutiao.com/search?keyword=我国全超导磁体刷新世界纪录","word":"我国全超导磁体刷新世界纪录"},{"url":"https://so.toutiao.com/search?keyword=网友吐槽折叠屏手机在东北被冻坏","word":"网友吐槽折叠屏手机在东北被冻坏"},{"url":"https://so.toutiao.com/search?keyword=长期喝桶装水有什么风险","word":"长期喝桶装水有什么风险"},{"url":"https://so.toutiao.com/search?keyword=“斩杀线”到底坑害了谁","word":"“斩杀线”到底坑害了谁"},{"url":"https://so.toutiao.com/search?keyword=贵金属市场短暂回调后强势企稳","word":"贵金属市场短暂回调后强势企稳"},{"url":"https://so.toutiao.com/search?keyword=博主：欧盟自食能源豪赌恶果","word":"博主：欧盟自食能源豪赌恶果"},{"url":"https://so.toutiao.com/search?keyword=对一头狼来说重返狼群是最好的结局","word":"对一头狼来说重返狼群是最好的结局"},{"url":"https://so.toutiao.com/search?keyword=全国基本养老保险参保人数达10.76亿","word":"全国基本养老保险参保人数达10.76亿"},{"url":"https://so.toutiao.com/search?keyword=前小摩策略师警告白银年内恐腰斩","word":"前小摩策略师警告白银年内恐腰斩"},{"url":"https://so.toutiao.com/search?keyword=经济增长主引擎%20动力足","word":"经济增长主引擎 动力足"},{"url":"https://so.toutiao.com/search?keyword=欧盟被曝起内讧","word":"欧盟被曝起内讧"},{"url":"https://so.toutiao.com/search?keyword=德选择党：泽连斯基要为北溪爆炸买单","word":"德选择党：泽连斯基要为北溪爆炸买单"},{"url":"https://so.toutiao.com/search?keyword=专家解读印度尼帕病毒疫情","word":"专家解读印度尼帕病毒疫情"},{"url":"https://so.toutiao.com/search?keyword=印度尼帕病毒疫情会失控吗","word":"印度尼帕病毒疫情会失控吗"},{"url":"https://so.toutiao.com/search?keyword=U23国足抵京%20多位七旬球迷接机","word":"U23国足抵京 多位七旬球迷接机"},{"url":"https://so.toutiao.com/search?keyword=席卷印度的尼帕疫情是怎么回事","word":"席卷印度的尼帕疫情是怎么回事"},{"url":"https://so.toutiao.com/search?keyword=南部战区回应菲组织所谓“联合巡航”","word":"南部战区回应菲组织所谓“联合巡航”"},{"url":"https://so.toutiao.com/search?keyword=武汉至上海有“夜间列车”了","word":"武汉至上海有“夜间列车”了"},{"url":"https://so.toutiao.com/search?keyword=无锡首次开行至香港高铁直达列车","word":"无锡首次开行至香港高铁直达列车"},{"url":"https://so.toutiao.com/search?keyword=银行理财率先打响存款“争夺战”","word":"银行理财率先打响存款“争夺战”"},{"url":"https://so.toutiao.com/search?keyword=世卫组织：饮用生枣椰汁前务必煮沸","word":"世卫组织：饮用生枣椰汁前务必煮沸"},{"url":"https://so.toutiao.com/search?keyword=火箭距西部第二仅差2个胜场","word":"火箭距西部第二仅差2个胜场"},{"url":"https://so.toutiao.com/search?keyword=傅聪：台湾回归中国在法理上牢牢锁定","word":"傅聪：台湾回归中国在法理上牢牢锁定"},{"url":"https://so.toutiao.com/search?keyword=网友晒车子智驾失灵撞向环卫工","word":"网友晒车子智驾失灵撞向环卫工"},{"url":"https://so.toutiao.com/search?keyword=中方在联合国驳斥日本涉台错误言论","word":"中方在联合国驳斥日本涉台错误言论"},{"url":"https://so.toutiao.com/search?keyword=分析师：白银会在2月逐步见顶","word":"分析师：白银会在2月逐步见顶"},{"url":"https://so.toutiao.com/search?keyword=黄晓明妈妈夸赵丽颖","word":"黄晓明妈妈夸赵丽颖"},{"url":"https://so.toutiao.com/search?keyword=世卫称尼帕病毒或引发全球大流行","word":"世卫称尼帕病毒或引发全球大流行"},{"url":"https://so.toutiao.com/search?keyword=如何看待南非暂退G20","word":"如何看待南非暂退G20"},{"url":"https://so.toutiao.com/search?keyword=深圳南山成我国首个万亿GDP地市辖区","word":"深圳南山成我国首个万亿GDP地市辖区"},{"url":"https://so.toutiao.com/search?keyword=广深港高铁何以重塑大湾区","word":"广深港高铁何以重塑大湾区"},{"url":"https://so.toutiao.com/search?keyword=女子免疫系统攻击胚胎8年4次流产","word":"女子免疫系统攻击胚胎8年4次流产"},{"url":"https://so.toutiao.com/search?keyword=马化腾献唱“冲冲冲”激情扔公仔","word":"马化腾献唱“冲冲冲”激情扔公仔"},{"url":"https://so.toutiao.com/search?keyword=黄金彻底疯了%20还能上车吗","word":"黄金彻底疯了 还能上车吗"},{"url":"https://so.toutiao.com/search?keyword=蔡正元：民进党玩“精神胜利法”","word":"蔡正元：民进党玩“精神胜利法”"},{"url":"https://so.toutiao.com/search?keyword=印度尼帕患者疑误饮蝙蝠污染饮料","word":"印度尼帕患者疑误饮蝙蝠污染饮料"},{"url":"https://so.toutiao.com/search?keyword=冷空气将携大范围雨雪影响我国","word":"冷空气将携大范围雨雪影响我国"},{"url":"https://so.toutiao.com/search?keyword=印媒：中国在关税乱局中证明了实力","word":"印媒：中国在关税乱局中证明了实力"},{"url":"https://so.toutiao.com/search?keyword=女子行李箱藏40万现金出境被查","word":"女子行李箱藏40万现金出境被查"},{"url":"https://so.toutiao.com/search?keyword=A股半导体板块获青睐","word":"A股半导体板块获青睐"},{"url":"https://so.toutiao.com/search?keyword=靖国神社前的石狮掠自中国","word":"靖国神社前的石狮掠自中国"},{"url":"https://so.toutiao.com/search?keyword=东契奇谈海斯扣篮：我以为他会扣飞的","word":"东契奇谈海斯扣篮：我以为他会扣飞的"},{"url":"https://so.toutiao.com/search?keyword=马化腾：希望重现当年微信红包盛况","word":"马化腾：希望重现当年微信红包盛况"},{"url":"https://so.toutiao.com/search?keyword=美伊局势进入“关键一周”","word":"美伊局势进入“关键一周”"},{"url":"https://so.toutiao.com/search?keyword=日本预制菜为何能成为全民日常","word":"日本预制菜为何能成为全民日常"},{"url":"https://so.toutiao.com/search?keyword=印度增购阵风为何被自家媒体泼冷水","word":"印度增购阵风为何被自家媒体泼冷水"},{"url":"https://so.toutiao.com/search?keyword=中国代表在安理会向日方发出灵魂四问","word":"中国代表在安理会向日方发出灵魂四问"},{"url":"https://so.toutiao.com/search?keyword=智利当地人会吃车厘子吗","word":"智利当地人会吃车厘子吗"},{"url":"https://so.toutiao.com/search?keyword=美总统会下决心对伊朗动武吗","word":"美总统会下决心对伊朗动武吗"},{"url":"https://so.toutiao.com/search?keyword=小孩哥手搓望远镜观测到月球陨石坑","word":"小孩哥手搓望远镜观测到月球陨石坑"},{"url":"https://so.toutiao.com/search?keyword=安踏以15亿欧元收购PUMA%20SE股权","word":"安踏以15亿欧元收购PUMA SE股权"},{"url":"https://so.toutiao.com/search?keyword=海关查获旅客携带未申报人民币40万元","word":"海关查获旅客携带未申报人民币40万元"},{"url":"https://so.toutiao.com/search?keyword=局势升级%20伊朗或封锁霍尔木兹海峡","word":"局势升级 伊朗或封锁霍尔木兹海峡"},{"url":"https://so.toutiao.com/search?keyword=人社部：推动修订职工带薪年休假条例","word":"人社部：推动修订职工带薪年休假条例"},{"url":"https://so.toutiao.com/search?keyword=女子母亲去世爸爸悉心照料坐月子","word":"女子母亲去世爸爸悉心照料坐月子"},{"url":"https://so.toutiao.com/search?keyword=人社部：去年就业形势保持总体稳定","word":"人社部：去年就业形势保持总体稳定"},{"url":"https://so.toutiao.com/search?keyword=每天靠墙蹲一蹲有啥好处","word":"每天靠墙蹲一蹲有啥好处"},{"url":"https://so.toutiao.com/search?keyword=中国游客在巴厘岛中招脏水病","word":"中国游客在巴厘岛中招脏水病"},{"url":"https://so.toutiao.com/search?keyword=孩子长期用AI会变笨吗","word":"孩子长期用AI会变笨吗"},{"url":"https://so.toutiao.com/search?keyword=华晨宇殷秀梅手挽手下班","word":"华晨宇殷秀梅手挽手下班"},{"url":"https://so.toutiao.com/search?keyword=专家谈日本导弹“模拟命中”我军舰","word":"专家谈日本导弹“模拟命中”我军舰"},{"url":"https://so.toutiao.com/search?keyword=日本列车与卡车相撞%204名中国公民受伤","word":"日本列车与卡车相撞 4名中国公民受伤"},{"url":"https://so.toutiao.com/search?keyword=妻子发现亡夫生前给女店员8年转11万","word":"妻子发现亡夫生前给女店员8年转11万"},{"url":"https://so.toutiao.com/search?keyword=手机SIM卡里真有黄金吗","word":"手机SIM卡里真有黄金吗"},{"url":"https://so.toutiao.com/search?keyword=大湾区2025经济总量预计破15万亿元","word":"大湾区2025经济总量预计破15万亿元"},{"url":"https://so.toutiao.com/search?keyword=解放军潜艇压迫感拉满","word":"解放军潜艇压迫感拉满"},{"url":"https://so.toutiao.com/search?keyword=节前消费市场活力十足","word":"节前消费市场活力十足"},{"url":"https://so.toutiao.com/search?keyword=詹姆斯砍24分%20湖人终结公牛4连胜","word":"詹姆斯砍24分 湖人终结公牛4连胜"},{"url":"https://so.toutiao.com/search?keyword=职业伤害保障试点将扩大到全国","word":"职业伤害保障试点将扩大到全国"},{"url":"https://so.toutiao.com/search?keyword=iPhone%204S在拼多多卖爆","word":"iPhone 4S在拼多多卖爆"},{"url":"https://so.toutiao.com/search?keyword=业内：芯片普涨时代来临","word":"业内：芯片普涨时代来临"},{"url":"https://so.toutiao.com/search?keyword=国足1胜2平结束拉练","word":"国足1胜2平结束拉练"},{"url":"https://so.toutiao.com/search?keyword=火箭逆转灰熊%20申京轰33+9+6","word":"火箭逆转灰熊 申京轰33+9+6"},{"url":"https://so.toutiao.com/search?keyword=日本北海道暴雪7000旅客滞留机场","word":"日本北海道暴雪7000旅客滞留机场"},{"url":"https://so.toutiao.com/search?keyword=幼儿园举办创意冰壶比赛欢乐爆棚","word":"幼儿园举办创意冰壶比赛欢乐爆棚"},{"url":"https://so.toutiao.com/search?keyword=周也王玉雯巴黎秀场同框","word":"周也王玉雯巴黎秀场同框"},{"url":"https://so.toutiao.com/search?keyword=金价冲高回落是见顶还是最后的蓄力","word":"金价冲高回落是见顶还是最后的蓄力"},{"url":"https://so.toutiao.com/search?keyword=媒体人：翟晓川双腿全有拉伤","word":"媒体人：翟晓川双腿全有拉伤"},{"url":"https://so.toutiao.com/search?keyword=出生不久的宝宝一看妈妈就笑","word":"出生不久的宝宝一看妈妈就笑"},{"url":"https://so.toutiao.com/search?keyword=分析称金价急剧回调可能性正在增加","word":"分析称金价急剧回调可能性正在增加"},{"url":"https://so.toutiao.com/search?keyword=三项社保基金累计结余10.2万亿元","word":"三项社保基金累计结余10.2万亿元"},{"url":"https://so.toutiao.com/search?keyword=前欧委会主席：美欧关系正跌至冰点","word":"前欧委会主席：美欧关系正跌至冰点"},{"url":"https://so.toutiao.com/search?keyword=智能手表监测睡眠靠谱吗","word":"智能手表监测睡眠靠谱吗"},{"url":"https://so.toutiao.com/search?keyword=多项劳动者权益保障政策将出台","word":"多项劳动者权益保障政策将出台"},{"url":"https://so.toutiao.com/search?keyword=紫金矿业拟收购联合黄金100%股权","word":"紫金矿业拟收购联合黄金100%股权"},{"url":"https://so.toutiao.com/search?keyword=应对人工智能影响促就业文件将出台","word":"应对人工智能影响促就业文件将出台"},{"url":"https://so.toutiao.com/search?keyword=日本千叶县确认高致病性禽流感疫情","word":"日本千叶县确认高致病性禽流感疫情"},{"url":"https://so.toutiao.com/search?keyword=国民党民代怒批顾立雄“装神弄鬼”","word":"国民党民代怒批顾立雄“装神弄鬼”"},{"url":"https://so.toutiao.com/search?keyword=日本国内没有大熊猫了","word":"日本国内没有大熊猫了"},{"url":"https://so.toutiao.com/search?keyword=山西球迷赛后向北京球员吐口水","word":"山西球迷赛后向北京球员吐口水"},{"url":"https://so.toutiao.com/search?keyword=腾讯进场%20AI社交时代正在到来","word":"腾讯进场 AI社交时代正在到来"},{"url":"https://so.toutiao.com/search?keyword=京沪高铁再提速有何深意","word":"京沪高铁再提速有何深意"},{"url":"https://so.toutiao.com/search?keyword=美总统宣布对韩国加征关税","word":"美总统宣布对韩国加征关税"},{"url":"https://so.toutiao.com/search?keyword=日本首相再次就台湾问题大放厥词","word":"日本首相再次就台湾问题大放厥词"},{"url":"https://so.toutiao.com/search?keyword=怎么看“成都公交减速等赶车女子”","word":"怎么看“成都公交减速等赶车女子”"},{"url":"https://so.toutiao.com/search?keyword=北京一“胖改”永辉暂停营业","word":"北京一“胖改”永辉暂停营业"},{"url":"https://so.toutiao.com/search?keyword=新婚夫妻晨起遇门口蹲守双猫","word":"新婚夫妻晨起遇门口蹲守双猫"},{"url":"https://so.toutiao.com/search?keyword=专家：美总统“假动作”戏耍欧洲","word":"专家：美总统“假动作”戏耍欧洲"},{"url":"https://so.toutiao.com/search?keyword=为什么有些人的血管容易堵","word":"为什么有些人的血管容易堵"},{"url":"https://so.toutiao.com/search?keyword=专家：警惕银价短期“闪崩”风险","word":"专家：警惕银价短期“闪崩”风险"},{"url":"https://so.toutiao.com/search?keyword=今年是工业金属大年吗","word":"今年是工业金属大年吗"},{"url":"https://so.toutiao.com/search?keyword=台北101照见“台独”的穷途末路","word":"台北101照见“台独”的穷途末路"},{"url":"https://so.toutiao.com/search?keyword=全国征兵(女兵)进行中","word":"全国征兵(女兵)进行中"},{"url":"https://so.toutiao.com/search?keyword=黄蜂130-93轻取76人","word":"黄蜂130-93轻取76人"},{"url":"https://so.toutiao.com/search?keyword=河南大姐回应请雪天滞留司机吃饭","word":"河南大姐回应请雪天滞留司机吃饭"},{"url":"https://so.toutiao.com/search?keyword=建议广东建设中国预制菜第一省","word":"建议广东建设中国预制菜第一省"},{"url":"https://so.toutiao.com/search?keyword=什么是肝脓肿","word":"什么是肝脓肿"},{"url":"https://so.toutiao.com/search?keyword=美国若对伊朗动武将面临哪些后果","word":"美国若对伊朗动武将面临哪些后果"},{"url":"https://so.toutiao.com/search?keyword=姥姥外出6小时回家抱着外孙抹泪","word":"姥姥外出6小时回家抱着外孙抹泪"},{"url":"https://so.toutiao.com/search?keyword=谷爱凌袒露赛场背后的心声","word":"谷爱凌袒露赛场背后的心声"},{"url":"https://so.toutiao.com/search?keyword=邵佳一国足首份答卷能给100分吗","word":"邵佳一国足首份答卷能给100分吗"},{"url":"https://so.toutiao.com/search?keyword=斩杀线的另一个名字叫做资本主义","word":"斩杀线的另一个名字叫做资本主义"},{"url":"https://so.toutiao.com/search?keyword=36岁孕妈肝脏被8斤血管瘤侵噬","word":"36岁孕妈肝脏被8斤血管瘤侵噬"},{"url":"https://so.toutiao.com/search?keyword=歌手陈雪凝老公发文承认有一个孩子","word":"歌手陈雪凝老公发文承认有一个孩子"},{"url":"https://so.toutiao.com/search?keyword=媒体人谈徐昕无缘南区首发原因","word":"媒体人谈徐昕无缘南区首发原因"},{"url":"https://so.toutiao.com/search?keyword=米兰冬奥会中国体育代表团成立","word":"米兰冬奥会中国体育代表团成立"},{"url":"https://so.toutiao.com/search?keyword=曝车王舒马赫已可借助轮椅活动","word":"曝车王舒马赫已可借助轮椅活动"},{"url":"https://so.toutiao.com/search?keyword=小孩哥卡在财神爷“掌心”出不来","word":"小孩哥卡在财神爷“掌心”出不来"},{"url":"https://so.toutiao.com/search?keyword=俞敏洪称AI+教育会消灭大量老师岗","word":"俞敏洪称AI+教育会消灭大量老师岗"},{"url":"https://so.toutiao.com/search?keyword=龙门石窟台阶敲出防滑纹","word":"龙门石窟台阶敲出防滑纹"},{"url":"https://so.toutiao.com/search?keyword=偷税老板被查抱电脑逃跑%20员工删文件","word":"偷税老板被查抱电脑逃跑 员工删文件"},{"url":"https://so.toutiao.com/search?keyword=法国猫咪在西班牙走丢后徒步回家","word":"法国猫咪在西班牙走丢后徒步回家"},{"url":"https://so.toutiao.com/search?keyword=外交部提醒春节避免前往日本","word":"外交部提醒春节避免前往日本"},{"url":"https://so.toutiao.com/search?keyword=美股三大指数集体收涨","word":"美股三大指数集体收涨"},{"url":"https://so.toutiao.com/search?keyword=研究发现睡眠对寿命的影响仅次于吸烟","word":"研究发现睡眠对寿命的影响仅次于吸烟"},{"url":"https://so.toutiao.com/search?keyword=2026马年从正月初一开始","word":"2026马年从正月初一开始"},{"url":"https://so.toutiao.com/search?keyword=北约秘书长称欧洲防务自主纯属做梦","word":"北约秘书长称欧洲防务自主纯属做梦"},{"url":"https://so.toutiao.com/search?keyword=卡尼：加中关系为两国人民创造机遇","word":"卡尼：加中关系为两国人民创造机遇"},{"url":"https://so.toutiao.com/search?keyword=黄晓明Angelababy带小海绵游迪士尼","word":"黄晓明Angelababy带小海绵游迪士尼"},{"url":"https://so.toutiao.com/search?keyword=中国代表在安理会敦促日方反思纠错","word":"中国代表在安理会敦促日方反思纠错"},{"url":"https://so.toutiao.com/search?keyword=黄金结构性存款里面有哪些门道","word":"黄金结构性存款里面有哪些门道"},{"url":"https://so.toutiao.com/search?keyword=两个00后“刮腻子”年入100多万","word":"两个00后“刮腻子”年入100多万"},{"url":"https://so.toutiao.com/search?keyword=中国机器人进化有多快","word":"中国机器人进化有多快"},{"url":"https://so.toutiao.com/search?keyword=光伏企业如何不被白银绑架","word":"光伏企业如何不被白银绑架"},{"url":"https://so.toutiao.com/search?keyword=49条中日航线取消全部航班","word":"49条中日航线取消全部航班"},{"url":"https://so.toutiao.com/search?keyword=如何防范尼帕病毒","word":"如何防范尼帕病毒"},{"url":"https://so.toutiao.com/search?keyword=卢昱晓发千字长文告别《轧戏》胡羞","word":"卢昱晓发千字长文告别《轧戏》胡羞"},{"url":"https://so.toutiao.com/search?keyword=男子非法捕猎猕猴%20家中发现野猪肉","word":"男子非法捕猎猕猴 家中发现野猪肉"},{"url":"https://so.toutiao.com/search?keyword=拜合拉木李昊签名从队头签到了队尾","word":"拜合拉木李昊签名从队头签到了队尾"},{"url":"https://so.toutiao.com/search?keyword=乌将战时状态和总动员令再延长90天","word":"乌将战时状态和总动员令再延长90天"},{"url":"https://so.toutiao.com/search?keyword=美称未排除外交解决伊朗问题可能性","word":"美称未排除外交解决伊朗问题可能性"},{"url":"https://so.toutiao.com/search?keyword=北京成功举办四大洲花样滑冰锦标赛","word":"北京成功举办四大洲花样滑冰锦标赛"},{"url":"https://so.toutiao.com/search?keyword=北京后卫陈盈骏13中6拿到14分4板6助","word":"北京后卫陈盈骏13中6拿到14分4板6助"},{"url":"https://so.toutiao.com/search?keyword=土耳其外长会见哈马斯代表团","word":"土耳其外长会见哈马斯代表团"},{"url":"https://so.toutiao.com/search?keyword=男子发现妻子每天上厕所顺路存1000","word":"男子发现妻子每天上厕所顺路存1000"},{"url":"https://so.toutiao.com/search?keyword=尼帕病毒一般社交接触传播效率较低","word":"尼帕病毒一般社交接触传播效率较低"},{"url":"https://so.toutiao.com/search?keyword=“长晋高速大客车侧翻2死6伤”不实","word":"“长晋高速大客车侧翻2死6伤”不实"},{"url":"https://so.toutiao.com/search?keyword=92岁“睡美人”每天睡觉超20小时","word":"92岁“睡美人”每天睡觉超20小时"},{"url":"https://so.toutiao.com/search?keyword=女子瞒着老公带俩孩子开车8小时见面","word":"女子瞒着老公带俩孩子开车8小时见面"},{"url":"https://so.toutiao.com/search?keyword=大爷2.58万买“宝马”5天停半路4次","word":"大爷2.58万买“宝马”5天停半路4次"},{"url":"https://so.toutiao.com/search?keyword=我国已将尼帕病毒纳入检测范围","word":"我国已将尼帕病毒纳入检测范围"},{"url":"https://so.toutiao.com/search?keyword=张雨绮被曝代孕","word":"张雨绮被曝代孕"},{"url":"https://so.toutiao.com/search?keyword=芬兰为何主动“敲响”中国的门","word":"芬兰为何主动“敲响”中国的门"},{"url":"https://so.toutiao.com/search?keyword=大兴安岭猞猁每天“打卡”检查站","word":"大兴安岭猞猁每天“打卡”检查站"},{"url":"https://so.toutiao.com/search?keyword=女子打“透视”麻将被牌友抓包","word":"女子打“透视”麻将被牌友抓包"},{"url":"https://so.toutiao.com/search?keyword=约谈当保安的毕业生？武汉理工回应","word":"约谈当保安的毕业生？武汉理工回应"},{"url":"https://so.toutiao.com/search?keyword=国企董事长上门殴打他人被行拘3天","word":"国企董事长上门殴打他人被行拘3天"},{"url":"https://so.toutiao.com/search?keyword=胖东来的黄金“阳谋”","word":"胖东来的黄金“阳谋”"},{"url":"https://so.toutiao.com/search?keyword=印度尼帕病毒疫情或来自医院","word":"印度尼帕病毒疫情或来自医院"},{"url":"https://so.toutiao.com/search?keyword=北京航空航天大学原校长李未院士逝世","word":"北京航空航天大学原校长李未院士逝世"},{"url":"https://so.toutiao.com/search?keyword=中方回应美威胁对加拿大征100％关税","word":"中方回应美威胁对加拿大征100％关税"},{"url":"https://so.toutiao.com/search?keyword=特朗普与奥巴马克林顿呛声","word":"特朗普与奥巴马克林顿呛声"},{"url":"https://so.toutiao.com/search?keyword=“饿死肿瘤”的方法真的找到了吗","word":"“饿死肿瘤”的方法真的找到了吗"},{"url":"https://so.toutiao.com/search?keyword=传奇赛车手舒马赫或已醒","word":"传奇赛车手舒马赫或已醒"},{"url":"https://so.toutiao.com/search?keyword=印度阅兵女子摩托车方阵表演叠罗汉","word":"印度阅兵女子摩托车方阵表演叠罗汉"},{"url":"https://so.toutiao.com/search?keyword=金属或迎新一轮“超级周期”","word":"金属或迎新一轮“超级周期”"},{"url":"https://so.toutiao.com/search?keyword=菲律宾客船倾覆事故已致18人死亡","word":"菲律宾客船倾覆事故已致18人死亡"},{"url":"https://so.toutiao.com/search?keyword=紫金矿业总市值突破万亿","word":"紫金矿业总市值突破万亿"},{"url":"https://so.toutiao.com/search?keyword=印度街头“千万富翁”乞丐被抓","word":"印度街头“千万富翁”乞丐被抓"},{"url":"https://so.toutiao.com/search?keyword=全年业绩预计大幅增长公司名单","word":"全年业绩预计大幅增长公司名单"},{"url":"https://so.toutiao.com/search?keyword=男子去世后账户被保姆转走50万","word":"男子去世后账户被保姆转走50万"},{"url":"https://so.toutiao.com/search?keyword=首个肺结节辅助诊断试剂盒获批上市","word":"首个肺结节辅助诊断试剂盒获批上市"},{"url":"https://so.toutiao.com/search?keyword=美国离“内战”有多远","word":"美国离“内战”有多远"},{"url":"https://so.toutiao.com/search?keyword=稀土价格持续上涨%20行业龙头扭亏为盈","word":"稀土价格持续上涨 行业龙头扭亏为盈"},{"url":"https://so.toutiao.com/search?keyword=欧盟印度力争敲定“所有协议之母”","word":"欧盟印度力争敲定“所有协议之母”"},{"url":"https://so.toutiao.com/search?keyword=东部战区官兵：家族三代期盼统一","word":"东部战区官兵：家族三代期盼统一"},{"url":"https://so.toutiao.com/search?keyword=旅客带近4斤黄金被海关查获","word":"旅客带近4斤黄金被海关查获"},{"url":"https://so.toutiao.com/search?keyword=国际刑院：杜特尔特下月面临听证会","word":"国际刑院：杜特尔特下月面临听证会"},{"url":"https://so.toutiao.com/search?keyword=新郎新娘坐马车意外翻进沟里","word":"新郎新娘坐马车意外翻进沟里"},{"url":"https://so.toutiao.com/search?keyword=小米店员自信展示手机防摔功能","word":"小米店员自信展示手机防摔功能"},{"url":"https://so.toutiao.com/search?keyword=高铁香港段连接内地站点增至110个","word":"高铁香港段连接内地站点增至110个"},{"url":"https://so.toutiao.com/search?keyword=你身边有动手能力强的孩子吗","word":"你身边有动手能力强的孩子吗"},{"url":"https://so.toutiao.com/search?keyword=新手司机1500元把车托运回老家","word":"新手司机1500元把车托运回老家"},{"url":"https://so.toutiao.com/search?keyword=美稀土公司称将加快建设美本土供应链","word":"美稀土公司称将加快建设美本土供应链"},{"url":"https://so.toutiao.com/search?keyword=金价破5000美元%20短期投资者何去何从","word":"金价破5000美元 短期投资者何去何从"},{"url":"https://so.toutiao.com/search?keyword=严寒来袭%20美流浪汉靠木板和破衣维生","word":"严寒来袭 美流浪汉靠木板和破衣维生"},{"url":"https://so.toutiao.com/search?keyword=有金店一边涨价一边打折","word":"有金店一边涨价一边打折"},{"url":"https://so.toutiao.com/search?keyword=国投白银LOF再发停牌公告","word":"国投白银LOF再发停牌公告"},{"url":"https://so.toutiao.com/search?keyword=警方：正侦办夫妻吃娃娃菜中毒案","word":"警方：正侦办夫妻吃娃娃菜中毒案"},{"url":"https://so.toutiao.com/search?keyword=你如何看U23亚洲杯日本队球员实力","word":"你如何看U23亚洲杯日本队球员实力"},{"url":"https://so.toutiao.com/search?keyword=北美极寒来袭%20尼亚加拉大瀑布被冻住","word":"北美极寒来袭 尼亚加拉大瀑布被冻住"},{"url":"https://so.toutiao.com/search?keyword=德防长：建议特朗普道歉但不抱希望","word":"德防长：建议特朗普道歉但不抱希望"},{"url":"https://so.toutiao.com/search?keyword=媒体：“失能补贴”申领有点太复杂","word":"媒体：“失能补贴”申领有点太复杂"},{"url":"https://so.toutiao.com/search?keyword=国乒19岁小将温瑞博排名连升七位","word":"国乒19岁小将温瑞博排名连升七位"},{"url":"https://so.toutiao.com/search?keyword=黄金暴涨背后的美元信任危机","word":"黄金暴涨背后的美元信任危机"},{"url":"https://so.toutiao.com/search?keyword=车企日系三强为何分化加剧","word":"车企日系三强为何分化加剧"},{"url":"https://so.toutiao.com/search?keyword=海岛小县取消中考背后有个大趋势","word":"海岛小县取消中考背后有个大趋势"},{"url":"https://so.toutiao.com/search?keyword=评论员谈浙江一地普高“全员直升”","word":"评论员谈浙江一地普高“全员直升”"},{"url":"https://so.toutiao.com/search?keyword=媒体：绿营为维护美国不惜抹黑大陆","word":"媒体：绿营为维护美国不惜抹黑大陆"},{"url":"https://so.toutiao.com/search?keyword=《小城大事》40集大结局是什么","word":"《小城大事》40集大结局是什么"}]