[{"url":"https://so.toutiao.com/search?keyword=中方强烈谴责瓜达尔港袭击事件","word":"中方强烈谴责瓜达尔港袭击事件"},{"url":"https://so.toutiao.com/search?keyword=央行将开展8000亿元买断式逆回购操作","word":"央行将开展8000亿元买断式逆回购操作"},{"url":"https://so.toutiao.com/search?keyword=2026年中央一号文件发布","word":"2026年中央一号文件发布"},{"url":"https://so.toutiao.com/search?keyword=春运路上：电车亏电%20油车没油","word":"春运路上：电车亏电 油车没油"},{"url":"https://so.toutiao.com/search?keyword=研究：人类寿命长短超50%由基因决定","word":"研究：人类寿命长短超50%由基因决定"},{"url":"https://so.toutiao.com/search?keyword=父亲去世%20女儿回大伯家过年泪流满面","word":"父亲去世 女儿回大伯家过年泪流满面"},{"url":"https://so.toutiao.com/search?keyword=灵隐寺对38万爽约者出手了","word":"灵隐寺对38万爽约者出手了"},{"url":"https://so.toutiao.com/search?keyword=中国男篮能击败日本队吗","word":"中国男篮能击败日本队吗"},{"url":"https://so.toutiao.com/search?keyword=李微漪确认狼王格林离世","word":"李微漪确认狼王格林离世"},{"url":"https://so.toutiao.com/search?keyword=无人机和机器人首次写入中央一号文件","word":"无人机和机器人首次写入中央一号文件"},{"url":"https://so.toutiao.com/search?keyword=多地网传“人贩子出没”系谣言","word":"多地网传“人贩子出没”系谣言"},{"url":"https://so.toutiao.com/search?keyword=爱泼斯坦案“吃人”传闻怎么来的","word":"爱泼斯坦案“吃人”传闻怎么来的"},{"url":"https://so.toutiao.com/search?keyword=演员马如龙49岁儿子在家中去世","word":"演员马如龙49岁儿子在家中去世"},{"url":"https://so.toutiao.com/search?keyword=马斯克被法司法部门传唤","word":"马斯克被法司法部门传唤"},{"url":"https://so.toutiao.com/search?keyword=记者卧底精神病医院许多病人无异常","word":"记者卧底精神病医院许多病人无异常"},{"url":"https://so.toutiao.com/search?keyword=为什么现在的猪肉不香了","word":"为什么现在的猪肉不香了"},{"url":"https://so.toutiao.com/search?keyword=爱泼斯坦豪宅内景黑暗又诡异","word":"爱泼斯坦豪宅内景黑暗又诡异"},{"url":"https://so.toutiao.com/search?keyword=郑丽文：感受到大陆十足的诚意跟善意","word":"郑丽文：感受到大陆十足的诚意跟善意"},{"url":"https://so.toutiao.com/search?keyword=胡兵瞿颖街拍被大爷催发喜糖","word":"胡兵瞿颖街拍被大爷催发喜糖"},{"url":"https://so.toutiao.com/search?keyword=24岁模特因“太老”被爱泼斯坦拒绝","word":"24岁模特因“太老”被爱泼斯坦拒绝"},{"url":"https://so.toutiao.com/search?keyword=设计方回应大S纪念雕像被指不像本人","word":"设计方回应大S纪念雕像被指不像本人"},{"url":"https://so.toutiao.com/search?keyword=女老板开宝马住高端小区多次超市偷窃","word":"女老板开宝马住高端小区多次超市偷窃"},{"url":"https://so.toutiao.com/search?keyword=JF-17订单意向激增%20巴铁面临甜蜜烦恼","word":"JF-17订单意向激增 巴铁面临甜蜜烦恼"},{"url":"https://so.toutiao.com/search?keyword=李微微受贿超1亿被判无期徒刑","word":"李微微受贿超1亿被判无期徒刑"},{"url":"https://so.toutiao.com/search?keyword=马斯克被女儿爆料曾登爱泼斯坦岛","word":"马斯克被女儿爆料曾登爱泼斯坦岛"},{"url":"https://so.toutiao.com/search?keyword=中央一号文件：严查挤占挪用涉农资金","word":"中央一号文件：严查挤占挪用涉农资金"},{"url":"https://so.toutiao.com/search?keyword=六角恐龙掉马桶%20女子耗时2小时抓住","word":"六角恐龙掉马桶 女子耗时2小时抓住"},{"url":"https://so.toutiao.com/search?keyword=男子买盆栽苹果树%20苹果竟插上去的","word":"男子买盆栽苹果树 苹果竟插上去的"},{"url":"https://so.toutiao.com/search?keyword=中央一号文件规范承包地经营权流转","word":"中央一号文件规范承包地经营权流转"},{"url":"https://so.toutiao.com/search?keyword=的哥早年听广播买30多克黄金已全卖","word":"的哥早年听广播买30多克黄金已全卖"},{"url":"https://so.toutiao.com/search?keyword=克林顿夫妇同意为爱泼斯坦案作证","word":"克林顿夫妇同意为爱泼斯坦案作证"},{"url":"https://so.toutiao.com/search?keyword=黄金会不会套住一代人","word":"黄金会不会套住一代人"},{"url":"https://so.toutiao.com/search?keyword=婚礼上女方父母当场退还女婿给的彩礼","word":"婚礼上女方父母当场退还女婿给的彩礼"},{"url":"https://so.toutiao.com/search?keyword=男子10年收集12块石头拼“天然时钟”","word":"男子10年收集12块石头拼“天然时钟”"},{"url":"https://so.toutiao.com/search?keyword=广州白云机场工作人员集体换上汉服","word":"广州白云机场工作人员集体换上汉服"},{"url":"https://so.toutiao.com/search?keyword=韩国女团成员称为保持身材吃一周冰块","word":"韩国女团成员称为保持身材吃一周冰块"},{"url":"https://so.toutiao.com/search?keyword=4.5万善款4.4万被中间人“抽走”","word":"4.5万善款4.4万被中间人“抽走”"},{"url":"https://so.toutiao.com/search?keyword=这波黄金疯涨真结束了吗","word":"这波黄金疯涨真结束了吗"},{"url":"https://so.toutiao.com/search?keyword=小伙将腿全部纹黑后开始起皮","word":"小伙将腿全部纹黑后开始起皮"},{"url":"https://so.toutiao.com/search?keyword=车门储物格放水瓶有多危险","word":"车门储物格放水瓶有多危险"},{"url":"https://so.toutiao.com/search?keyword=女子网购羽绒服上竟有“孝”字臂章","word":"女子网购羽绒服上竟有“孝”字臂章"},{"url":"https://so.toutiao.com/search?keyword=中国军人即使穿着便衣依旧气场全开","word":"中国军人即使穿着便衣依旧气场全开"},{"url":"https://so.toutiao.com/search?keyword=英国首相访华花4天在日仅停7小时","word":"英国首相访华花4天在日仅停7小时"},{"url":"https://so.toutiao.com/search?keyword=女子网购9斤香蕉到货仅1根","word":"女子网购9斤香蕉到货仅1根"},{"url":"https://so.toutiao.com/search?keyword=中央一号文件聚焦优化农村中小学布局","word":"中央一号文件聚焦优化农村中小学布局"},{"url":"https://so.toutiao.com/search?keyword=如何看待新一批爱泼斯坦文件公开","word":"如何看待新一批爱泼斯坦文件公开"},{"url":"https://so.toutiao.com/search?keyword=第一批回家过年的人已堵在沪昆高速","word":"第一批回家过年的人已堵在沪昆高速"},{"url":"https://so.toutiao.com/search?keyword=中共中央国务院：规范农产品直播带货","word":"中共中央国务院：规范农产品直播带货"},{"url":"https://so.toutiao.com/search?keyword=北约军队驻乌时间披露%20俄罗斯发声","word":"北约军队驻乌时间披露 俄罗斯发声"},{"url":"https://so.toutiao.com/search?keyword=美国女子曝幼年被母亲喂食人肉","word":"美国女子曝幼年被母亲喂食人肉"},{"url":"https://so.toutiao.com/search?keyword=男子无座绿皮火车上站着睡着","word":"男子无座绿皮火车上站着睡着"},{"url":"https://so.toutiao.com/search?keyword=10岁女孩连续3年用压岁钱买黄金","word":"10岁女孩连续3年用压岁钱买黄金"},{"url":"https://so.toutiao.com/search?keyword=俄一架重型运输机抵达古巴空军基地","word":"俄一架重型运输机抵达古巴空军基地"},{"url":"https://so.toutiao.com/search?keyword=国共机制化交流为两岸关系注入暖流","word":"国共机制化交流为两岸关系注入暖流"},{"url":"https://so.toutiao.com/search?keyword=马里宁米兰赛前成功完成4A","word":"马里宁米兰赛前成功完成4A"},{"url":"https://so.toutiao.com/search?keyword=广东男篮主场负于上海男篮遭遇两连败","word":"广东男篮主场负于上海男篮遭遇两连败"},{"url":"https://so.toutiao.com/search?keyword=吴克群请环卫大姐们吃饭还发红包","word":"吴克群请环卫大姐们吃饭还发红包"},{"url":"https://so.toutiao.com/search?keyword=《嘉禾望岗》创作人解读流量密码","word":"《嘉禾望岗》创作人解读流量密码"},{"url":"https://so.toutiao.com/search?keyword=阿雅发文缅怀大S","word":"阿雅发文缅怀大S"},{"url":"https://so.toutiao.com/search?keyword=美媒：老詹若能助尼克斯夺冠就是GOAT","word":"美媒：老詹若能助尼克斯夺冠就是GOAT"},{"url":"https://so.toutiao.com/search?keyword=iPhone单季度市场份额是三星530%","word":"iPhone单季度市场份额是三星530%"},{"url":"https://so.toutiao.com/search?keyword=你认为最有效的启蒙教育是什么","word":"你认为最有效的启蒙教育是什么"},{"url":"https://so.toutiao.com/search?keyword=深圳北站凌晨5点挤满返乡人","word":"深圳北站凌晨5点挤满返乡人"},{"url":"https://so.toutiao.com/search?keyword=3岁宝宝在天安门前向兵哥哥敬礼","word":"3岁宝宝在天安门前向兵哥哥敬礼"},{"url":"https://so.toutiao.com/search?keyword=东鹏饮料：林戴钦持股比例降至4.84%","word":"东鹏饮料：林戴钦持股比例降至4.84%"},{"url":"https://so.toutiao.com/search?keyword=巴黎检方传唤马斯克要其接受问询","word":"巴黎检方传唤马斯克要其接受问询"},{"url":"https://so.toutiao.com/search?keyword=新疆拟追授贺娇龙记大功奖励","word":"新疆拟追授贺娇龙记大功奖励"}]