[{"url":"https://so.toutiao.com/search?keyword=罗技这回真的要凉了吗","word":"罗技这回真的要凉了吗"},{"url":"https://so.toutiao.com/search?keyword=歼10C遭外机雷达照射%20飞行员以牙还牙","word":"歼10C遭外机雷达照射 飞行员以牙还牙"},{"url":"https://so.toutiao.com/search?keyword=中国人工智能走在世界前列","word":"中国人工智能走在世界前列"},{"url":"https://so.toutiao.com/search?keyword=马杜罗夫妇关押地如“人间炼狱”","word":"马杜罗夫妇关押地如“人间炼狱”"},{"url":"https://so.toutiao.com/search?keyword=孩子生病妈妈碰运气买彩票中500万","word":"孩子生病妈妈碰运气买彩票中500万"},{"url":"https://so.toutiao.com/search?keyword=伊朗称霍尔木兹海峡已经关闭","word":"伊朗称霍尔木兹海峡已经关闭"},{"url":"https://so.toutiao.com/search?keyword=郭永航被查","word":"郭永航被查"},{"url":"https://so.toutiao.com/search?keyword=“玉芬”系列神曲全网播放10多亿次","word":"“玉芬”系列神曲全网播放10多亿次"},{"url":"https://so.toutiao.com/search?keyword=老人患帕金森8年靠脑机接口走稳","word":"老人患帕金森8年靠脑机接口走稳"},{"url":"https://so.toutiao.com/search?keyword=中国发布芯片研发突破成果","word":"中国发布芯片研发突破成果"},{"url":"https://so.toutiao.com/search?keyword=连云港查获46亿元稀土走私案不实","word":"连云港查获46亿元稀土走私案不实"},{"url":"https://so.toutiao.com/search?keyword=西班牙女子被性侵多次后申请安乐死","word":"西班牙女子被性侵多次后申请安乐死"},{"url":"https://so.toutiao.com/search?keyword=罗技为“降价像狗一样跑来”广告道歉","word":"罗技为“降价像狗一样跑来”广告道歉"},{"url":"https://so.toutiao.com/search?keyword=何润东直播回应项羽一角翻红","word":"何润东直播回应项羽一角翻红"},{"url":"https://so.toutiao.com/search?keyword=猪肉降价你会囤货吗","word":"猪肉降价你会囤货吗"},{"url":"https://so.toutiao.com/search?keyword=吴京面部被按压后出现缓慢回弹凹陷","word":"吴京面部被按压后出现缓慢回弹凹陷"},{"url":"https://so.toutiao.com/search?keyword=教育部重申严禁宣传高考状元和升学率","word":"教育部重申严禁宣传高考状元和升学率"},{"url":"https://so.toutiao.com/search?keyword=清明快到了你会去给思念的人扫墓吗","word":"清明快到了你会去给思念的人扫墓吗"},{"url":"https://so.toutiao.com/search?keyword=猪价为啥这么低","word":"猪价为啥这么低"},{"url":"https://so.toutiao.com/search?keyword=大学生表白被拒后怒砸食堂咖啡店","word":"大学生表白被拒后怒砸食堂咖啡店"},{"url":"https://so.toutiao.com/search?keyword=郭麒麟对接回应ktv传闻","word":"郭麒麟对接回应ktv传闻"},{"url":"https://so.toutiao.com/search?keyword=女子手指截肢放肚里养1个月变小肉球","word":"女子手指截肢放肚里养1个月变小肉球"},{"url":"https://so.toutiao.com/search?keyword=比亚迪2025年营收突破8000亿元","word":"比亚迪2025年营收突破8000亿元"},{"url":"https://so.toutiao.com/search?keyword=一中国博士后遭美方盘问后自杀身亡","word":"一中国博士后遭美方盘问后自杀身亡"},{"url":"https://so.toutiao.com/search?keyword=“雪山救狐狸”是个什么梗","word":"“雪山救狐狸”是个什么梗"},{"url":"https://so.toutiao.com/search?keyword=女儿去世后母亲花光退休金网购","word":"女儿去世后母亲花光退休金网购"},{"url":"https://so.toutiao.com/search?keyword=女子提醒男子静音车厢内别喧哗","word":"女子提醒男子静音车厢内别喧哗"},{"url":"https://so.toutiao.com/search?keyword=美官员忧对伊作战战斧导弹消耗过快","word":"美官员忧对伊作战战斧导弹消耗过快"},{"url":"https://so.toutiao.com/search?keyword=匈牙利总理：中国不可战胜","word":"匈牙利总理：中国不可战胜"},{"url":"https://so.toutiao.com/search?keyword=中国男足开始触底反弹了吗","word":"中国男足开始触底反弹了吗"},{"url":"https://so.toutiao.com/search?keyword=手机回收暗藏信息泄露风险","word":"手机回收暗藏信息泄露风险"},{"url":"https://so.toutiao.com/search?keyword=《隐身的名字》值得看吗","word":"《隐身的名字》值得看吗"},{"url":"https://so.toutiao.com/search?keyword=全红婵19岁生日杂志封面揭晓","word":"全红婵19岁生日杂志封面揭晓"},{"url":"https://so.toutiao.com/search?keyword=鱼塘被无人机喷药致鱼死亡%20当地回应","word":"鱼塘被无人机喷药致鱼死亡 当地回应"},{"url":"https://so.toutiao.com/search?keyword=夫妻在服务区停车10分钟被盗1800元","word":"夫妻在服务区停车10分钟被盗1800元"},{"url":"https://so.toutiao.com/search?keyword=自动翻炒锅上线实现1人看管4锅","word":"自动翻炒锅上线实现1人看管4锅"},{"url":"https://so.toutiao.com/search?keyword=菲律宾警方发现失踪中国商人遗体","word":"菲律宾警方发现失踪中国商人遗体"},{"url":"https://so.toutiao.com/search?keyword=中国地面无人作战实力有多强","word":"中国地面无人作战实力有多强"},{"url":"https://so.toutiao.com/search?keyword=杨德龙：目前还是反弹行情","word":"杨德龙：目前还是反弹行情"},{"url":"https://so.toutiao.com/search?keyword=老人骨盆骨折护士直接提腰带搬运","word":"老人骨盆骨折护士直接提腰带搬运"},{"url":"https://so.toutiao.com/search?keyword=山东“5·27”重大爆炸事故原因公布","word":"山东“5·27”重大爆炸事故原因公布"},{"url":"https://so.toutiao.com/search?keyword=媒体：傲慢就是罗技的坟墓","word":"媒体：傲慢就是罗技的坟墓"},{"url":"https://so.toutiao.com/search?keyword=CBA联赛山东男篮94-100不敌山西队","word":"CBA联赛山东男篮94-100不敌山西队"},{"url":"https://so.toutiao.com/search?keyword=燃料危机下印度面临艰难抉择","word":"燃料危机下印度面临艰难抉择"},{"url":"https://so.toutiao.com/search?keyword=周杰伦《那天下雨了》回应《晴天》","word":"周杰伦《那天下雨了》回应《晴天》"},{"url":"https://so.toutiao.com/search?keyword=北京男篮96-93险胜广东","word":"北京男篮96-93险胜广东"},{"url":"https://so.toutiao.com/search?keyword=“粉底液将军”为何会激起群嘲","word":"“粉底液将军”为何会激起群嘲"},{"url":"https://so.toutiao.com/search?keyword=原第二炮兵政治部主任韩友庆逝世","word":"原第二炮兵政治部主任韩友庆逝世"},{"url":"https://so.toutiao.com/search?keyword=伊朗就IAEA总干事不当言论发出警告","word":"伊朗就IAEA总干事不当言论发出警告"},{"url":"https://so.toutiao.com/search?keyword=媒体：闯中使馆日本人绝非凭空冒出来","word":"媒体：闯中使馆日本人绝非凭空冒出来"},{"url":"https://so.toutiao.com/search?keyword=楼市“小阳春”真的来了吗","word":"楼市“小阳春”真的来了吗"},{"url":"https://so.toutiao.com/search?keyword=《逐玉》到底有什么特别之处","word":"《逐玉》到底有什么特别之处"},{"url":"https://so.toutiao.com/search?keyword=小鹏MONA%20M03实车曝光","word":"小鹏MONA M03实车曝光"}]